{
    "Ar36": {
        "error": 0.0024752098745125122, 
        "filter_outliers_dict": {
            "filter_outliers": true, 
            "iterations": 2, 
            "std_devs": 2
        }, 
        "fit": "Parabolic", 
        "value": 1.2084808409585661
    }, 
    "Ar37": {
        "error": 0.011302175600006365, 
        "filter_outliers_dict": {
            "filter_outliers": true, 
            "iterations": 2, 
            "std_devs": 2
        }, 
        "fit": "linear", 
        "value": -0.7835213347485583
    }, 
    "Ar38": {
        "error": 0.012023093176442566, 
        "filter_outliers_dict": {
            "filter_outliers": true, 
            "iterations": 2, 
            "std_devs": 2
        }, 
        "fit": "linear", 
        "value": 0.09740008608147596
    }, 
    "Ar39": {
        "error": 0.024313022456732884, 
        "filter_outliers_dict": {
            "filter_outliers": true, 
            "iterations": 2, 
            "std_devs": 2
        }, 
        "fit": "Parabolic", 
        "value": -0.07621571550973437
    }, 
    "Ar40": {
        "error": 0.040412782915716046, 
        "filter_outliers_dict": {
            "filter_outliers": true, 
            "iterations": 2, 
            "std_devs": 2
        }, 
        "fit": "Parabolic", 
        "value": 361.99623976557905
    }
}